dbt_toolkit-0.1.4.data/scripts/dbt-toolkit
dbttoolkit/__init__.py
dbttoolkit/_version.py
dbttoolkit/cli.py
dbttoolkit/dbt_cloud/__init__.py
dbttoolkit/dbt_cloud/actions/__init__.py
dbttoolkit/dbt_cloud/actions/__main__.py
dbttoolkit/dbt_cloud/actions/_docs.py
dbttoolkit/dbt_cloud/actions/retrieve_artifacts_time_interval.py
dbttoolkit/dbt_cloud/actions/retrieve_most_recent_artifact.py
dbttoolkit/dbt_cloud/clients/__init__.py
dbttoolkit/dbt_cloud/clients/dbt_cloud_client.py
dbttoolkit/dbt_cloud/models/__init__.py
dbttoolkit/dbt_cloud/models/dbt_artifact.py
dbttoolkit/documentation/__init__.py
dbttoolkit/documentation/actions/__init__.py
dbttoolkit/documentation/actions/__main__.py
dbttoolkit/documentation/actions/propagate.py
dbttoolkit/documentation/models/__init__.py
dbttoolkit/documentation/models/column.py
dbttoolkit/documentation/presentation/__init__.py
dbttoolkit/documentation/presentation/formatters.py
dbttoolkit/documentation/presentation/stats.py
dbttoolkit/utils/__init__.py
dbttoolkit/utils/io.py
dbttoolkit/utils/logger.py
dbt_toolkit-0.1.4.dist-info/LICENSE
dbt_toolkit-0.1.4.dist-info/METADATA
dbt_toolkit-0.1.4.dist-info/WHEEL
dbt_toolkit-0.1.4.dist-info/top_level.txt
dbt_toolkit-0.1.4.dist-info/RECORD
