Metadata-Version: 2.1
Name: dbt-toolkit
Version: 0.1.4
Summary: Utilities for running dbt automations
Home-page: https://github.com/voi-oss/dbt-toolkit
Author: Voi Technology AB
Author-email: opensource@voiapp.io
License: Apache License, Version 2.0
Platform: UNKNOWN
Classifier: Development Status :: 3 - Alpha
Classifier: License :: OSI Approved :: Apache Software License
Classifier: Programming Language :: Python :: 3
Classifier: Programming Language :: Python :: 3.9
Classifier: Programming Language :: Python :: 3 :: Only
Requires-Python: >=3.8, <4
Requires-Dist: requests ~=2.28.0
Requires-Dist: typer ~=0.4.2
Requires-Dist: google-cloud-storage ~=2.4.0
Requires-Dist: pydantic ~=1.9.1
Requires-Dist: rich ~=13.3.5
